ft_package_chanwoong1/__init__.py
ft_package_chanwoong1/count_in_list.py
ft_package_chanwoong1-0.0.1.dist-info/LICENSE
ft_package_chanwoong1-0.0.1.dist-info/METADATA
ft_package_chanwoong1-0.0.1.dist-info/WHEEL
ft_package_chanwoong1-0.0.1.dist-info/top_level.txt
ft_package_chanwoong1-0.0.1.dist-info/RECORD
