Metadata-Version: 2.1
Name: ft-package-chanwoong1
Version: 0.0.1
Summary: A sample test package
Home-page: https://github.com/chanwoong1/ft_package
Author: chanwoong1
Author-email: jcw7468@gmail.com
License: MIT
Classifier: Programming Language :: Python :: 3
Classifier: License :: OSI Approved :: MIT License
Classifier: Operating System :: OS Independent
License-File: LICENSE
